libr/__init__.py
libr-0.0.0.dist-info/METADATA
libr-0.0.0.dist-info/WHEEL
libr-0.0.0.dist-info/top_level.txt
libr-0.0.0.dist-info/RECORD
