Metadata-Version: 2.1
Name: libr
Version: 0.0.0
Summary: libr
Home-page: https://github.com/
Author: libr
License: MIT
Keywords: libr
Classifier: Development Status :: 1 - Planning
Classifier: Intended Audience :: Developers
Classifier: Topic :: Software Development :: Build Tools
Classifier: License :: OSI Approved :: MIT License
Classifier: Programming Language :: Python :: 3
Classifier: Programming Language :: Python :: 3.7
